[[[[[[[{"title":"Test Title","text":"Test text"}],[{"title":"Test Title","text":"Test text"}]],[[{"title":"Test Title","text":"Test text"}],[{"title":"Test Title","text":"Test text"}]]]]]],{"id":"acd008d7-0e3a-4409-9c13-d7df544be4e3","title":"title","text":"text"},[[[[[[[{"title":"Test Title","text":"Test text"}],[{"title":"Test Title","text":"Test text"}]],[[{"title":"Test Title","text":"Test text"}],[{"title":"Test Title","text":"Test text"}]]]]]]],{"id":"7a894e04-1660-4185-ac44-88dd9a5eb64f","title":"another one","text":"another onee"},[[[[[[[{"title":"Test Title","text":"Test text"}],[{"title":"Test Title","text":"Test text"}]],[[{"title":"Test Title","text":"Test text"}],[{"title":"Test Title","text":"Test text"}]]]]]],{"id":"acd008d7-0e3a-4409-9c13-d7df544be4e3","title":"title","text":"text"},[[[[[[[{"title":"Test Title","text":"Test text"}],[{"title":"Test Title","text":"Test text"}]],[[{"title":"Test Title","text":"Test text"}],[{"title":"Test Title","text":"Test text"}]]]]]]]],{"id":"64afe0d9-748d-4ef5-b4ae-4de7c25123ba","title":"plz display","text":"thanks"},[[[[[[[{"title":"Test Title","text":"Test text"}],[{"title":"Test Title","text":"Test text"}]],[[{"title":"Test Title","text":"Test text"}],[{"title":"Test Title","text":"Test text"}]]]]]],{"id":"acd008d7-0e3a-4409-9c13-d7df544be4e3","title":"title","text":"text"},[[[[[[[{"title":"Test Title","text":"Test text"}],[{"title":"Test Title","text":"Test text"}]],[[{"title":"Test Title","text":"Test text"}],[{"title":"Test Title","text":"Test text"}]]]]]]],{"id":"7a894e04-1660-4185-ac44-88dd9a5eb64f","title":"another one","text":"another onee"},[[[[[[[{"title":"Test Title","text":"Test text"}],[{"title":"Test Title","text":"Test text"}]],[[{"title":"Test Title","text":"Test text"}],[{"title":"Test Title","text":"Test text"}]]]]]],{"id":"acd008d7-0e3a-4409-9c13-d7df544be4e3","title":"title","text":"text"},[[[[[[[{"title":"Test Title","text":"Test text"}],[{"title":"Test Title","text":"Test text"}]],[[{"title":"Test Title","text":"Test text"}],[{"title":"Test Title","text":"Test text"}]]]]]]]]]]